{"word":[{"name":"Ananya","word":15},{"name":"akshita","word":-1},{"name":"ananya","word":18},{"name":"akshita","word":32},{"name":"Player 1","word":45},{"name":"Player 2","word":34},{"name":"Player 1","word":22},{"name":"Player 2","word":39},{"name":"Player 1","word":22},{"name":"Player 2","word":-1},{"name":"Player 1","word":27},{"name":"Player 2","word":15},{"name":"Player 1","word":20},{"name":"Player 2","word":26},{"name":"Player 1","word":38},{"name":"Player 2","word":26},{"name":"Player 1","word":12},{"name":"Player 2","word":23},{"name":"Player 1","word":12},{"name":"Player 2","word":26},{"name":"Player 1","word":6},{"name":"Player 1","word":-1},{"name":"Player 2","word":12},{"name":"Player 1","word":9},{"name":"Player 1","word":21},{"name":"Player 1","word":-1},{"name":"Player 1","word":10},{"name":"Player 1","word":14},{"name":"Player 1","word":10},{"name":"Player 1","word":30},{"name":"Player 1","word":18},{"name":"Player 1","score":-1},{"name":"Player 1","score":12},{"name":"Player 1","word":"rad","score":4}],"game":[{"name":"Player 2","score":0},{"score":0},{"name":"Player 2","score":0},{"score":0},{"name":"Player 2","score":0},{"score":0},{"name":"Player 2","score":0},{"score":0},{"name":"Player 2","score":0},{"score":0},{"name":"Player 1","score":0},{"name":"Player 1","score":0},{"name":"Player 1","score":0},{"name":"Player 1","score":0},{"name":"Player 1","score":0},{"name":"Player 1","score":0},{"name":"Player 1","score":0},{"name":"Player 1","score":0},{"name":"ananya","score":33},{"name":"ananya","score":33},{"name":"Player 1","score":0},{"name":"Player 1","score":45},{"name":"Player 1","score":45},{"name":"Player 1","score":22},{"name":"Player 1","score":22},{"name":"Player 1","score":22},{"name":"Player 1","score":27},{"name":"Player 1","score":20},{"name":"Player 1","score":38},{"name":"Player 1","score":12},{"name":"Player 1","score":12},{"name":"Player 1","score":0},{"name":"Player 1","score":12},{"name":"Player 1","score":0},{"name":"Player 1","score":0},{"name":"Player 1","score":0},{"name":"Player 1","score":0},{"name":"Player 1","score":0},{"name":"Player 1","score":0},{"name":"Player 1","score":0},{"name":"Player 1","score":0},{"name":"Player 1","score":0},{"name":"Player 1","score":9},{"name":"Player 1","score":9},{"name":"Player 1","score":9},{"name":"Player 1","score":9},{"name":"Player 1","score":9},{"name":"Player 1","score":9},{"name":"Player 1","score":30},{"name":"Player 1","score":30},{"name":"Player 1","score":0},{"name":"Player 1","score":0},{"name":"Player 1","score":0},{"name":"Player 1","score":0},{"name":"Player 1","score":0},{"name":"Player 2","score":0},{"name":"Player 2","score":0},{"name":"Player 1","score":0},{"name":"Player 2","score":0},{"name":"Player 1","score":0},{"name":"Player 1","score":0},{"name":"Player 1","score":0},{"name":"Player 1","score":0},{"name":"Player 1","score":0},{"name":"Player 1","score":0},{"name":"Player 2","score":0},{"name":"Player 2","score":0},{"name":"Player 2","score":0},{"name":"Player 2","score":0},{"name":"Player 2","score":0},{"name":"Player 1","score":0},{"name":"Player 1","score":0},{"name":"Player 2","score":0},{"name":"Player 2","score":0}]}